Chandere-2.5.0a1.dist-info/DESCRIPTION.rst
Chandere-2.5.0a1.dist-info/METADATA
Chandere-2.5.0a1.dist-info/RECORD
Chandere-2.5.0a1.dist-info/WHEEL
Chandere-2.5.0a1.dist-info/entry_points.txt
Chandere-2.5.0a1.dist-info/metadata.json
Chandere-2.5.0a1.dist-info/top_level.txt
chandere/__init__.py
chandere/__main__.py
chandere/cli.py
chandere/errors.py
chandere/loader.py
chandere/main.py
chandere/output.py
