Metadata-Version: 2.0
Name: Chandere
Version: 2.5.0a1
Summary: An asynchronous image/file downloader and thread archiver for Futaba-styled imageboards, such as 4chan and 8chan.
Home-page: https://github.com/TsarFox/chandere
Author: Jakob Kreuze
Author-email: jakob@memeware.net
License: GPLv3+
Download-URL: https://github.com/TsarFox/chandere
Keywords: downloader archiver imageboard
Platform: UNKNOWN
Classifier: Development Status :: 5 - Production/Stable
Classifier: Environment :: Console
Classifier: Intended Audience :: End Users/Desktop
Classifier: License :: OSI Approved :: GNU General Public License v3 or later (GPLv3+)
Classifier: Natural Language :: English
Classifier: Programming Language :: Python
Classifier: Programming Language :: Python :: 3.6
Classifier: Topic :: Communications :: BBS
Classifier: Topic :: Internet :: WWW/HTTP
Classifier: Topic :: Internet :: WWW/HTTP :: Dynamic Content :: Message Boards
Classifier: Topic :: Text Processing
Classifier: Topic :: Utilities
Requires-Dist: aiohttp
